pyKinetics/__init__.py
pyKinetics/pyKinetics.py
pyKinetics-0.0.3.dist-info/LICENSE.txt
pyKinetics-0.0.3.dist-info/METADATA
pyKinetics-0.0.3.dist-info/WHEEL
pyKinetics-0.0.3.dist-info/top_level.txt
pyKinetics-0.0.3.dist-info/RECORD
