Metadata-Version: 2.1
Name: pyKinetics
Version: 0.0.3
Summary: A simple package that allows you to construct and simulate any biokinetical model.
Home-page: https://github.com/RuiFilipeCampos/pyKinetics
Author: Rui Filipe de Sousa Campos
Author-email: ruifilipedesousacampos@gmail.com
License: UNKNOWN
Platform: UNKNOWN
Classifier: Programming Language :: Python :: 3
Classifier: License :: OSI Approved :: MIT License
Classifier: Operating System :: OS Independent
Requires-Python: >=3.6
